test.py
x.py
bikidata/__init__.py
bikidata/__main__.py
bikidata/main.py
bikidata/mcp.py
bikidata/query.py
bikidata/rdf2vec.py
bikidata/semantic.py
bikidata-0.3.7.dist-info/licenses/LICENSE
scripts/index.py
scripts/map.py
bikidata-0.3.7.dist-info/METADATA
bikidata-0.3.7.dist-info/WHEEL
bikidata-0.3.7.dist-info/top_level.txt
bikidata-0.3.7.dist-info/RECORD
