Metadata-Version: 2.4
Name: bikidata
Version: 0.3.7
Summary: Developer-friendly Queries over RDF triples
Author-email: Etienne Posthumus <ep@epoz.org>
License: MIT
Project-URL: Homepage, https://github.com/ISE-FIZKarlsruhe/bikidata/
Project-URL: Repository, https://github.com/ISE-FIZKarlsruhe/bikidata/
Keywords: search,RDF,Linked Data
Requires-Python: >=3.10
License-File: LICENSE
Requires-Dist: duckdb>=1.3.2
Requires-Dist: numpy>=2.2.4
Requires-Dist: xxhash>=3.5.0
Requires-Dist: pandas>=2.2.3
Requires-Dist: cohere==5.15.0
Requires-Dist: redis>=6.4.0
Dynamic: license-file
